{"license":{"0":"LSO 01-005","1":"LSO 02-007A (rev2)","2":"LSO 03-008 (Rev.3)","3":"LSO 04-009 (rev.1)","4":"LSO 06-010 (Rev. 2)","5":"LSO 08-011","6":"LSO 09-012 (Rev 1)","7":"LSO 10-014","8":"LSO 14-015","9":"LSO 15-016"},"operator":{"0":"Harris Corporation","1":"Virginia Commercial Space Flight Authority","2":"Alaska Aerospace Development Corporation","3":"Mojave Air &amp; Space Port","4":"Oklahoma Space Industry Development Authority","5":"New Mexico Spaceflight Authority","6":"Jacksonville Aviation Authority","7":"Space Florida","8":"Midland International Airport","9":"Houston Airport System"},"expiration":{"0":"20210918","1":"20171218","2":"20180923","3":"20190616","4":"20210611","5":"20181214","6":"20200110","7":"20200630","8":"20190914","9":"20200625"},"location":{"0":"CA","1":"VA","2":"Alaska","3":"CA","4":"Oklahoma","5":"New Mexico","6":"Florida","7":"Florida","8":"TX","9":"TX"},"site":{"0":"California Spaceport","1":"Wallops Flight Facility","2":"Pacific Spaceport Complex Alaska","3":"Mojave Air &amp; Space Port","4":"Burns Flat, Oklahoma","5":"Spaceport America","6":"Cecil Field","7":"Cape Canaveral Air Force Station","8":"Midland International Airport","9":"Ellington Airport"}}